pysniffer/__init__.py
pysniffer/decorator.py
pysniffer/interfaces.py
pysniffer-0.2.0.dist-info/LICENSE.txt
pysniffer-0.2.0.dist-info/METADATA
pysniffer-0.2.0.dist-info/WHEEL
pysniffer-0.2.0.dist-info/top_level.txt
pysniffer-0.2.0.dist-info/RECORD
