Metadata-Version: 2.1
Name: pysniffer
Version: 0.2.0
Summary: A Python package for profiling and measuring function performance.
Home-page: https://github.com/DhananjayanOnline/pysniffer
Author: Dhananjay Haridas
Author-email: Dhananjay Haridas <mail.dhananjayharidas@gmail.com>
License: # Released under MIT License
Project-URL: Repository, https://github.com/DhananjayanOnline/pysniffer
Keywords: profiling,performance,benchmarking,memory usage,cProfile,tracemalloc
Classifier: Development Status :: 4 - Beta
Classifier: Intended Audience :: Developers
Classifier: License :: OSI Approved :: MIT License
Classifier: Programming Language :: Python :: 3
Classifier: Programming Language :: Python :: 3.8
Classifier: Programming Language :: Python :: 3.9
Classifier: Programming Language :: Python :: 3.10
Classifier: Programming Language :: Python :: 3.11
Classifier: Topic :: Software Development :: Libraries :: Python Modules
Classifier: Topic :: Software Development :: Quality Assurance
Requires-Python: >=3.6
License-File: LICENSE.txt
Requires-Dist: setuptools
Requires-Dist: wheel
